boardgame/__init__.py
boardgame/gameconfig.py
boardgame/gamecontroller.py
boardgame/gamemodel.py
boardgame/gameviewer.py
boardgame/player.py
boardgame/ai/__init__.py
boardgame/ai/limited_minimax.py
boardgame/ai/minimax.py
boardgame/ai/randomchoice.py
boardgame/commands/__init__.py
boardgame/commands/connectfour_commands.py
boardgame/commands/main.py
boardgame/commands/tictactoe_commands.py
boardgame/connectfour/__init__.py
boardgame/connectfour/connectfourmodel.py
boardgame/connectfour/connectfourviewer.py
boardgame/tictactoe/__init__.py
boardgame/tictactoe/tictactoemodel.py
boardgame/tictactoe/tictactoeviewer.py
boardgame-0.1.0.data/scripts/boardgame
boardgame-0.1.0.dist-info/DESCRIPTION.rst
boardgame-0.1.0.dist-info/METADATA
boardgame-0.1.0.dist-info/RECORD
boardgame-0.1.0.dist-info/WHEEL
boardgame-0.1.0.dist-info/metadata.json
boardgame-0.1.0.dist-info/top_level.txt
