Metadata-Version: 2.0
Name: boardgame
Version: 0.1.0
Summary: 
